ibsec/__init__.py
ibsec/__main__.py
ibsec/ibsec.py
ibsec-0.0.3.dist-info/LICENSE.txt
ibsec-0.0.3.dist-info/METADATA
ibsec-0.0.3.dist-info/WHEEL
ibsec-0.0.3.dist-info/entry_points.txt
ibsec-0.0.3.dist-info/top_level.txt
ibsec-0.0.3.dist-info/RECORD
