Metadata-Version: 2.1
Name: ibsec
Version: 0.0.3
Summary: Lookup security codes for Interactive Brokers
Home-page: https://github.com/dissolved/ibsec
Author: Ryan Sandridge
Author-email: noreply@ryansandridge.com
License: MIT
Platform: UNKNOWN
Classifier: License :: OSI Approved :: MIT License
Classifier: Programming Language :: Python :: 3
Classifier: Programming Language :: Python :: 3.8
Requires-Dist: fire (>=0.3.0)
Requires-Dist: pyperclip (>=1.8.0)
